{
    "বাংলাদেশ": [
        {
            "title": "প্রধানমন্ত্রীর উপদেষ্টাকে দিল্লিতে প্রবেশে বাধা দেওয়ায় ঢাকায় ভারতের ভারপ্রাপ্ত হাইকমিশনারকে তলব",
            "link": "https://www.bbc.co.uk/bengali/live/c892ygjjj9yt?at_medium=RSS&at_campaign=rss",
            "source": "বিবিসি বাংলা"
        },
        {
            "title": "ইসলামী ব্যাংকে দুই দফায় পাঁচ হাজার কোটি টাকা বিশেষ ধার, পরিচালনা পর্ষদ বিলুপ্ত - সামনে কী?",
            "link": "https://www.bbc.com/bengali/articles/cp36yy361e5o?at_medium=RSS&at_campaign=rss",
            "source": "বিবিসি বাংলা"
        },
        {
            "title": "এনসিপিআই নামের কোন অজানা দলে যোগ দিলেন তৃণমূল কংগ্রেসের 'বিদ্রোহীরা'?",
            "link": "https://www.bbc.com/bengali/articles/cx24x3n1ne0o?at_medium=RSS&at_campaign=rss",
            "source": "বিবিসি বাংলা"
        },
        {
            "title": "দিল্লি বিমানবন্দরে উপদেষ্টা জাহেদ উর রহমানকে বাধা, কী বলছে পররাষ্ট্র মন্ত্রণালয়",
            "link": "https://www.bbc.com/bengali/articles/crlwxdxek71o?at_medium=RSS&at_campaign=rss",
            "source": "বিবিসি বাংলা"
        },
        {
            "title": "'প্রেমিকের দায়িত্ব পালন ' - কানাডার ম্যাচ ছেড়ে কেটি পেরির পারফর্ম্যান্স দেখার সমালোচনার জবাবে ট্রুডো",
            "link": "https://www.bbc.com/bengali/articles/cewqkd7y8xzo?at_medium=RSS&at_campaign=rss",
            "source": "বিবিসি বাংলা"
        },
        {
            "title": "যুদ্ধ বন্ধে চুক্তির ঘোষণা যুক্তরাষ্ট্র ও ইরানের, শুক্রবার জেনেভায় স্বাক্ষর",
            "link": "https://www.bbc.com/bengali/articles/clywn948p7jo?at_medium=RSS&at_campaign=rss",
            "source": "বিবিসি বাংলা"
        }
    ],
    "আন্তর্জাতিক": [
        {
            "title": "Record daily jump in DRC Ebola outbreak takes death toll to 178",
            "link": "https://www.aljazeera.com/news/2026/6/15/record-daily-jump-in-drc-ebola-outbreak-takes-death-toll-to-178?traffic_source=rss",
            "source": "আল জাজিরা"
        },
        {
            "title": "Spain vs Cape Verde live: World Cup 2026",
            "link": "https://www.aljazeera.com/sports/liveblog/2026/6/15/spain-vs-cape-verde-live-world-cup-2026?traffic_source=rss",
            "source": "আল জাজিরা"
        },
        {
            "title": "Ebola risk for World Cup is ‘extremely low’, but US is ready, experts say",
            "link": "https://www.aljazeera.com/sports/2026/6/15/ebola-risk-for-world-cup-is-extremely-low-but-us-is-ready-experts-say?traffic_source=rss",
            "source": "আল জাজিরা"
        },
        {
            "title": "‘Island surrounded by war’: Crimeans panic amid Ukrainian attacks",
            "link": "https://www.aljazeera.com/news/2026/6/15/island-surrounded-by-war-crimeans-panic-amid-ukrainian-strikes?traffic_source=rss",
            "source": "আল জাজিরা"
        },
        {
            "title": "‘Netanyahu’s life project failed with US-Iran deal’",
            "link": "https://www.aljazeera.com/video/newsfeed/2026/6/15/netanyahus-life-project-failed-with-us-iran?traffic_source=rss",
            "source": "আল জাজিরা"
        },
        {
            "title": "Iran, US agree tentative deal to ‘end war’: Your questions answered",
            "link": "https://www.aljazeera.com/news/2026/6/15/iran-us-agree-tentative-deal-to-end-war-your-questions-answered?traffic_source=rss",
            "source": "আল জাজিরা"
        },
        {
            "title": "Oil prices fall and shares jump after US-Iran deal announced",
            "link": "https://www.bbc.com/news/articles/c6217106px6o?at_medium=RSS&at_campaign=rss",
            "source": "BBC World"
        },
        {
            "title": "Norwegian crown princess's son found guilty of two counts of rape",
            "link": "https://www.bbc.com/news/articles/cly9d10l5p4o?at_medium=RSS&at_campaign=rss",
            "source": "BBC World"
        },
        {
            "title": "Russian strikes kill 11 and set historic cathedral in Kyiv ablaze",
            "link": "https://www.bbc.com/news/articles/c4gy037gjz3o?at_medium=RSS&at_campaign=rss",
            "source": "BBC World"
        },
        {
            "title": "Brazil woman dies after rope-jumping instructors fail to attach cord",
            "link": "https://www.bbc.com/news/articles/c5yz4xelnveo?at_medium=RSS&at_campaign=rss",
            "source": "BBC World"
        },
        {
            "title": "US musician Oliver Tree dies in helicopter collision in Brazil",
            "link": "https://www.bbc.com/news/articles/cqj1dd5rgnzo?at_medium=RSS&at_campaign=rss",
            "source": "BBC World"
        },
        {
            "title": "South Korea's Starbucks to shut for staff history lesson after backlash",
            "link": "https://www.bbc.com/news/articles/ckg4n3pyjg9o?at_medium=RSS&at_campaign=rss",
            "source": "BBC World"
        }
    ],
    "খেলাধুলা": [
        {
            "title": "Jordan Cox, Sonny Baker to debut for England in second New Zealand Test",
            "link": "https://www.espncricinfo.com/ci/content/story/1541292.html?ex_cid=OTC-RSS",
            "source": "ESPN Cricinfo"
        },
        {
            "title": "Sammy pleased with West Indies' 'thoughtful and smart cricket' in T20I series decider",
            "link": "https://www.espncricinfo.com/ci/content/story/1541287.html?ex_cid=OTC-RSS",
            "source": "ESPN Cricinfo"
        },
        {
            "title": "'Not ready to give up this' - Lyon's hunger drives long road back",
            "link": "https://www.espncricinfo.com/ci/content/story/1541253.html?ex_cid=OTC-RSS",
            "source": "ESPN Cricinfo"
        },
        {
            "title": "CA and states agree 'in principle' to BBL privatisation but hurdles remain",
            "link": "https://www.espncricinfo.com/ci/content/story/1541272.html?ex_cid=OTC-RSS",
            "source": "ESPN Cricinfo"
        },
        {
            "title": "Connolly fights off cramps in innings of a lifetime",
            "link": "https://www.espncricinfo.com/ci/content/story/1541246.html?ex_cid=OTC-RSS",
            "source": "ESPN Cricinfo"
        },
        {
            "title": "Holder completes heist for West Indies after Joseph picks up five",
            "link": "https://www.espncricinfo.com/ci/content/story/1541255.html?ex_cid=OTC-RSS",
            "source": "ESPN Cricinfo"
        },
        {
            "title": "Fifa seeks explanation over VAR official's hand gesture",
            "link": "https://www.bbc.com/sport/football/articles/cy9rd8g1lwzo?at_medium=RSS&at_campaign=rss",
            "source": "BBC Sports"
        },
        {
            "title": "Cox and Baker to make Test debuts in second Test",
            "link": "https://www.bbc.com/sport/cricket/articles/c8721ejdqn0o?at_medium=RSS&at_campaign=rss",
            "source": "BBC Sports"
        },
        {
            "title": "Stones goes from brink of retirement to World Cup 'pure joy'",
            "link": "https://www.bbc.com/sport/football/articles/c24y192myrvo?at_medium=RSS&at_campaign=rss",
            "source": "BBC Sports"
        },
        {
            "title": "World Cup hydration breaks - who are the winners and losers?",
            "link": "https://www.bbc.com/sport/football/articles/c621620wr77o?at_medium=RSS&at_campaign=rss",
            "source": "BBC Sports"
        },
        {
            "title": "France star Mbappe vows to increase defensive work",
            "link": "https://www.bbc.com/sport/football/articles/cjegv7j5349o?at_medium=RSS&at_campaign=rss",
            "source": "BBC Sports"
        },
        {
            "title": "Cucurella joins Real Madrid - will Fernandez follow?",
            "link": "https://www.bbc.com/sport/football/articles/c3rynp1ex9ro?at_medium=RSS&at_campaign=rss",
            "source": "BBC Sports"
        }
    ],
    "প্রযুক্তি": [
        {
            "title": "As AI agents become employees, NewCore emerges with $66M to give them identities",
            "link": "https://techcrunch.com/2026/06/15/ai-agents-are-becoming-employees-newcore-emerges-with-66m-to-give-them-identities/",
            "source": "TechCrunch"
        },
        {
            "title": "A satellite just learned to find things on its own — here’s what that means",
            "link": "https://techcrunch.com/2026/06/15/a-satellite-just-learned-to-find-things-on-its-own-heres-what-that-means/",
            "source": "TechCrunch"
        },
        {
            "title": "The AI layoff wave is becoming a powder keg",
            "link": "https://techcrunch.com/2026/06/15/the-ai-layoff-wave-is-becoming-a-powder-keg/",
            "source": "TechCrunch"
        },
        {
            "title": "Orbio raises $21 million to automate hiring and onboarding for frontline workers",
            "link": "https://techcrunch.com/2026/06/14/orbio-raises-21-million-to-automate-hiring-and-onboarding-for-frontline-workers/",
            "source": "TechCrunch"
        },
        {
            "title": "Startup CEO Charlie Javice is reportedly angling for a Trump pardon",
            "link": "https://techcrunch.com/2026/06/14/startup-ceo-charlie-javice-is-reportedly-angling-for-a-trump-pardon/",
            "source": "TechCrunch"
        },
        {
            "title": "UK may ban social media for children under 16",
            "link": "https://techcrunch.com/2026/06/14/uk-may-ban-social-media-for-children-under-16/",
            "source": "TechCrunch"
        },
        {
            "title": "The Kratom Civil War Is Heating Up, and MAHA Has Picked a Side",
            "link": "https://www.wired.com/story/the-kratom-civil-war-is-heating-up-and-maha-has-picked-a-side/",
            "source": "Wired"
        },
        {
            "title": "How Apple Is Making Your Older iPhone Run Faster and Stay Alive Longer",
            "link": "https://www.wired.com/story/how-apple-is-making-your-older-iphone-run-faster-and-stay-alive-longer/",
            "source": "Wired"
        },
        {
            "title": "1 in 4 World Cup Matches Could Be Played in Dangerous Temperatures",
            "link": "https://www.wired.com/story/2026-fifa-world-cup-dangerous-temperatures-heat/",
            "source": "Wired"
        },
        {
            "title": "A Crypto Scam Targeted a Gay OnlyFans Star. Then His X Feed Was Flooded With ‘MAGA Propaganda’",
            "link": "https://www.wired.com/story/a-gay-onlyfans-star-got-hacked-then-his-x-account-started-spewing-maga-propaganda/",
            "source": "Wired"
        },
        {
            "title": "The US Government Is Letting a Key Data Center Regulation Expire",
            "link": "https://www.wired.com/story/the-us-government-is-letting-a-key-data-center-regulation-expire/",
            "source": "Wired"
        },
        {
            "title": "The UK Places a Sweeping Ban on Social Media for Kids Under 16",
            "link": "https://www.wired.com/story/uk-social-media-under-16-ban/",
            "source": "Wired"
        }
    ]
}