{
    "বাংলাদেশ": [
        {
            "title": "বাংলাদেশের মানুষ কাঁটাতার ভয় পায় না, শুভেন্দুর পাল্টায় বললেন হুমায়ুন",
            "link": "https://www.bbc.co.uk/bengali/live/cvgzvxxw75xt?at_medium=RSS&at_campaign=rss",
            "source": "বিবিসি বাংলা"
        },
        {
            "title": "বাংলাদেশে গরুর মাংস আমদানির দাবি উঠছে কেন",
            "link": "https://www.bbc.com/bengali/articles/cy92097qld9o?at_medium=RSS&at_campaign=rss",
            "source": "বিবিসি বাংলা"
        },
        {
            "title": "সোশাল মিডিয়া কীভাবে চলচ্চিত্র তারকা ভিজয়কে রাজনৈতিক শক্তিতে পরিণত করল",
            "link": "https://www.bbc.com/bengali/articles/c7v97v7yn2qo?at_medium=RSS&at_campaign=rss",
            "source": "বিবিসি বাংলা"
        },
        {
            "title": "মুখ্যমন্ত্রী হয়েই কেন বাংলাদেশ সীমান্তে কাঁটাতারের বেড়া দিতে চাইছেন শুভেন্দু",
            "link": "https://www.bbc.com/bengali/articles/c3r2p57q37po?at_medium=RSS&at_campaign=rss",
            "source": "বিবিসি বাংলা"
        },
        {
            "title": "'বেতন দিতে না পেরে লোক ছাঁটাই করে দিচ্ছে, এটা নিয়ে আমরাও ভয়ে আছি'",
            "link": "https://www.bbc.com/bengali/articles/cnvp12rv7r8o?at_medium=RSS&at_campaign=rss",
            "source": "বিবিসি বাংলা"
        },
        {
            "title": "স্বাভাবিক প্রসবের জন্য যেসব প্রস্তুতি  সহায়ক হতে পারে",
            "link": "https://www.bbc.com/bengali/articles/crlp3n6je8po?at_medium=RSS&at_campaign=rss",
            "source": "বিবিসি বাংলা"
        }
    ],
    "আন্তর্জাতিক": [
        {
            "title": "Iran war effect: Why is Modi asking Indians to avoid foreign trips, gold?",
            "link": "https://www.aljazeera.com/news/2026/5/11/iran-war-effect-why-is-modi-asking-indians-to-avoid-foreign-trips-gold?traffic_source=rss",
            "source": "আল জাজিরা"
        },
        {
            "title": "Is the US empire in the middle of a long decline?",
            "link": "https://www.aljazeera.com/video/the-bottom-line/2026/5/11/is-the-us-empire-in-the-middle-of-a-long-decline?traffic_source=rss",
            "source": "আল জাজিরা"
        },
        {
            "title": "Lebanon Latest",
            "link": "https://www.aljazeera.com/video/2026/5/11/lebanon-latest-2?traffic_source=rss",
            "source": "আল জাজিরা"
        },
        {
            "title": "Lebanese civil defence worker captures moment of Israeli strike",
            "link": "https://www.aljazeera.com/video/newsfeed/2026/5/11/lebanese-civil-defence-worker-captures-moment-of-israeli-strike?traffic_source=rss",
            "source": "আল জাজিরা"
        },
        {
            "title": "Israel pushes for hangings and ‘show trials’ for ‘October 7 detainees’",
            "link": "https://www.aljazeera.com/news/2026/5/11/israel-pushes-for-death-penalty-and-show-trials-for-oct-7-detainees?traffic_source=rss",
            "source": "আল জাজিরা"
        },
        {
            "title": "Cole Allen pleads not guilty to ‌Trump attempted assassination",
            "link": "https://www.aljazeera.com/news/2026/5/11/suspect-pleads-not-guilty-to-attempted-assassination-of-us-president?traffic_source=rss",
            "source": "আল জাজিরা"
        },
        {
            "title": "US and French nationals test positive for hantavirus after leaving ship",
            "link": "https://www.bbc.com/news/articles/cjep78l5835o?at_medium=RSS&at_campaign=rss",
            "source": "BBC World"
        },
        {
            "title": "Portrait looted by Nazis found in home of Dutch SS leader's descendants",
            "link": "https://www.bbc.com/news/articles/cgmpj0p9k08o?at_medium=RSS&at_campaign=rss",
            "source": "BBC World"
        },
        {
            "title": "Washington dinner shooting suspect pleads not guilty",
            "link": "https://www.bbc.com/news/articles/c4g48ewgz8mo?at_medium=RSS&at_campaign=rss",
            "source": "BBC World"
        },
        {
            "title": "Whales could be harmed by diverted ships avoiding Middle East, scientists warn",
            "link": "https://www.bbc.com/news/articles/cz02dkkd9j9o?at_medium=RSS&at_campaign=rss",
            "source": "BBC World"
        },
        {
            "title": "Trump calls Iran response to US proposal to end war 'totally unacceptable'",
            "link": "https://www.bbc.com/news/articles/clypgz9e5pmo?at_medium=RSS&at_campaign=rss",
            "source": "BBC World"
        },
        {
            "title": "Dozens of Nigerian fishermen feared dead after Chad air strikes on Boko Haram",
            "link": "https://www.bbc.com/news/articles/cr5p85v446ro?at_medium=RSS&at_campaign=rss",
            "source": "BBC World"
        }
    ],
    "খেলাধুলা": [
        {
            "title": "Ashraful backs Bangladesh to beat the clock and Pakistan in rainy Mirpur",
            "link": "https://www.espncricinfo.com/ci/content/story/1536319.html?ex_cid=OTC-RSS",
            "source": "ESPN Cricinfo"
        },
        {
            "title": "Stonehouse called up to ODI squad as Wong is sent for hamstring scan",
            "link": "https://www.espncricinfo.com/ci/content/story/1536312.html?ex_cid=OTC-RSS",
            "source": "ESPN Cricinfo"
        },
        {
            "title": "DC opt to bowl; Dwarshuis to make PBKS debut",
            "link": "https://www.espncricinfo.com/ci/content/story/1536310.html?ex_cid=OTC-RSS",
            "source": "ESPN Cricinfo"
        },
        {
            "title": "Can SRH's power-hitters flip the script against red-hot GT?",
            "link": "https://www.espncricinfo.com/ci/content/story/1536307.html?ex_cid=OTC-RSS",
            "source": "ESPN Cricinfo"
        },
        {
            "title": "Hannon-Dalby seals thumping win as Warwickshire complete turnaround",
            "link": "https://www.espncricinfo.com/ci/content/story/1536293.html?ex_cid=OTC-RSS",
            "source": "ESPN Cricinfo"
        },
        {
            "title": "Draw on the cards, but Mominul and Shanto extend Bangladesh's lead",
            "link": "https://www.espncricinfo.com/ci/content/story/1536244.html?ex_cid=OTC-RSS",
            "source": "ESPN Cricinfo"
        },
        {
            "title": "Biggest VAR call ever? Four chaotic minutes that may define the season",
            "link": "https://www.bbc.com/sport/football/articles/c0m2rkwm87po?at_medium=RSS&at_campaign=rss",
            "source": "BBC Sports"
        },
        {
            "title": "West Ham set to contact referees' body over disallowed goal",
            "link": "https://www.bbc.com/sport/football/articles/c5yrxkg6z1eo?at_medium=RSS&at_campaign=rss",
            "source": "BBC Sports"
        },
        {
            "title": "The summer a golden generation lost its shine",
            "link": "https://www.bbc.co.uk/sport/extra/60s97qhdbf/the-golden-generation?at_medium=RSS&at_campaign=rss",
            "source": "BBC Sports"
        },
        {
            "title": "'It breaks my heart' – legend Mead to leave Arsenal",
            "link": "https://www.bbc.com/sport/football/articles/cm2p62jq70qo?at_medium=RSS&at_campaign=rss",
            "source": "BBC Sports"
        },
        {
            "title": "Ex-goalkeeper Martyn savours England cricket call",
            "link": "https://www.bbc.com/sport/articles/czd2335v1rmo?at_medium=RSS&at_campaign=rss",
            "source": "BBC Sports"
        },
        {
            "title": "How Flick's reshaped Barca dominated La Liga again",
            "link": "https://www.bbc.com/sport/football/articles/cedp2wjepqno?at_medium=RSS&at_campaign=rss",
            "source": "BBC Sports"
        }
    ],
    "প্রযুক্তি": [
        {
            "title": "NYT’s Wordle to become a TV game show",
            "link": "https://techcrunch.com/2026/05/11/nyts-wordle-to-become-a-tv-game-show/",
            "source": "TechCrunch"
        },
        {
            "title": "TikTok launches an ad-free subscription plan in the UK",
            "link": "https://techcrunch.com/2026/05/11/tiktok-launches-an-ad-free-subscription-plan-in-the-uk/",
            "source": "TechCrunch"
        },
        {
            "title": "There aren’t enough rockets for space data centers. Cowboy Space raised $275 million to build them.",
            "link": "https://techcrunch.com/2026/05/11/there-arent-enough-rockets-for-space-data-centers-cowboy-space-raised-275-million-to-build-them/",
            "source": "TechCrunch"
        },
        {
            "title": "Discord launches Nitro Rewards, giving subscribers access to the base tier of Xbox Game Pass for no extra cost",
            "link": "https://techcrunch.com/2026/05/11/discord-launches-nitro-rewards-giving-subscribers-access-to-the-base-tier-of-xbox-game-pass-for-no-extra-cost/",
            "source": "TechCrunch"
        },
        {
            "title": "Venmo’s biggest makeover in years comes at a very interesting time",
            "link": "https://techcrunch.com/2026/05/11/venmos-biggest-makeover-in-years-comes-at-a-very-interesting-time/",
            "source": "TechCrunch"
        },
        {
            "title": "Korea’s biggest manufacturers back Config, the TSMC of robot data",
            "link": "https://techcrunch.com/2026/05/11/koreas-biggest-manufacturers-back-config-the-tsmc-of-robot-data/",
            "source": "TechCrunch"
        },
        {
            "title": "Papa Johns Is Getting Into Drone Delivery—but Not for Pizza",
            "link": "https://www.wired.com/story/papa-johns-is-getting-into-drone-delivery-but-its-not-flying-pizza/",
            "source": "Wired"
        },
        {
            "title": "A Chevron Texas Power Plant Seeks School District Tax Break",
            "link": "https://www.wired.com/story/chevron-wants-school-district-tax-break-data-center-power-plant-texas/",
            "source": "Wired"
        },
        {
            "title": "CUDA Proves Nvidia Is a Software Company",
            "link": "https://www.wired.com/story/cuda-proves-nvidia-is-a-software-company/",
            "source": "Wired"
        },
        {
            "title": "I Work in Hollywood. Everyone Who Used to Make TV Is Now Secretly Training AI",
            "link": "https://www.wired.com/story/i-work-in-hollywood-everyone-who-used-to-make-tv-now-training-ai/",
            "source": "Wired"
        },
        {
            "title": "Keyboard Shortcuts I Learned From My Cat",
            "link": "https://www.wired.com/story/keyboard-shortcuts-i-learned-from-my-cat/",
            "source": "Wired"
        },
        {
            "title": "Could Contact-Tracing Apps Help With the Hantavirus? Not Really",
            "link": "https://www.wired.com/story/could-contact-tracing-apps-help-with-the-hantavirus-not-really/",
            "source": "Wired"
        }
    ]
}